{
  "meta": {
    "run_name": "aptq_resnet56",
    "backbone": "resnet56",
    "dataset_name": "cifar10",
    "seed": 42,
    "method": "aptq",
    "method_opts": {},
    "best_val": 0.915,
    "best_epoch": 197,
    "test_acc": 0.9184,
    "final_sparsity": 0.918298636163984,
    "final_ops": {
      "mul": 987776,
      "add": 11229408,
      "shift": 10237536,
      "mul_G": 0.000987776,
      "add_G": 0.011229408,
      "shift_G": 0.010237536,
      "energy_pJ": 15092118.080000002,
      "energy_GpJ": 0.015092118080000001,
      "sparsity": 0.918298636163984
    },
    "n_params": 1706202
  },
  "log": [
    {
      "epoch": 0,
      "tr_loss": 1.9937840591158185,
      "tr_acc": 0.23540178571428572,
      "val_loss": 2.2176942138671873,
      "val_acc": 0.2088,
      "time": 27.98390030860901
    },
    {
      "epoch": 1,
      "tr_loss": 1.7227977657318114,
      "tr_acc": 0.3480803571428571,
      "val_loss": 1.8340344829559325,
      "val_acc": 0.342,
      "time": 19.269713878631592
    },
    {
      "epoch": 2,
      "tr_loss": 1.4331179305485318,
      "tr_acc": 0.47299107142857144,
      "val_loss": 1.458269747543335,
      "val_acc": 0.4592,
      "time": 19.45171308517456
    },
    {
      "epoch": 3,
      "tr_loss": 1.218626173564366,
      "tr_acc": 0.5577232142857143,
      "val_loss": 1.4839648818969726,
      "val_acc": 0.4948,
      "time": 20.091394901275635
    },
    {
      "epoch": 4,
      "tr_loss": 1.0456676653453283,
      "tr_acc": 0.62640625,
      "val_loss": 1.252260876083374,
      "val_acc": 0.5472,
      "time": 19.018522024154663
    },
    {
      "epoch": 5,
      "tr_loss": 0.9627939592088972,
      "tr_acc": 0.6577008928571428,
      "val_loss": 1.2898876476287842,
      "val_acc": 0.5216,
      "time": 19.26459789276123
    },
    {
      "epoch": 6,
      "tr_loss": 0.8935285707882472,
      "tr_acc": 0.6849776785714285,
      "val_loss": 1.4032021627426148,
      "val_acc": 0.5242,
      "time": 19.272752285003662
    },
    {
      "epoch": 7,
      "tr_loss": 0.8332562232017517,
      "tr_acc": 0.7059375,
      "val_loss": 1.1433871517181395,
      "val_acc": 0.6174,
      "time": 19.050518035888672
    },
    {
      "epoch": 8,
      "tr_loss": 0.7819110114233835,
      "tr_acc": 0.725,
      "val_loss": 1.4788523086547851,
      "val_acc": 0.5338,
      "time": 19.42134714126587
    },
    {
      "epoch": 9,
      "tr_loss": 0.7244431107384818,
      "tr_acc": 0.7472544642857143,
      "val_loss": 0.9161803001403809,
      "val_acc": 0.6654,
      "time": 19.112706899642944
    },
    {
      "epoch": 10,
      "tr_loss": 0.6755594715050288,
      "tr_acc": 0.7642633928571428,
      "val_loss": 1.19750366897583,
      "val_acc": 0.6192,
      "time": 19.253743410110474
    },
    {
      "epoch": 11,
      "tr_loss": 0.6335984635353088,
      "tr_acc": 0.7802008928571429,
      "val_loss": 0.843198718547821,
      "val_acc": 0.708,
      "time": 19.60165238380432
    },
    {
      "epoch": 12,
      "tr_loss": 0.6046148005553654,
      "tr_acc": 0.7897544642857143,
      "val_loss": 1.2123872321128846,
      "val_acc": 0.6458,
      "time": 19.486478805541992
    },
    {
      "epoch": 13,
      "tr_loss": 0.5909344751494271,
      "tr_acc": 0.7945758928571428,
      "val_loss": 0.9704359892845154,
      "val_acc": 0.678,
      "time": 19.554444551467896
    },
    {
      "epoch": 14,
      "tr_loss": 0.5858258904729571,
      "tr_acc": 0.7967857142857143,
      "val_loss": 1.1236479070663452,
      "val_acc": 0.622,
      "time": 19.076266288757324
    },
    {
      "epoch": 15,
      "tr_loss": 0.5720591054643903,
      "tr_acc": 0.8011830357142857,
      "val_loss": 0.676223798084259,
      "val_acc": 0.7618,
      "time": 19.22930335998535
    },
    {
      "epoch": 16,
      "tr_loss": 0.5605935328347342,
      "tr_acc": 0.806875,
      "val_loss": 0.8730066955566407,
      "val_acc": 0.7082,
      "time": 19.34843921661377
    },
    {
      "epoch": 17,
      "tr_loss": 0.5392437454632351,
      "tr_acc": 0.8148660714285715,
      "val_loss": 0.8628582292556762,
      "val_acc": 0.7108,
      "time": 19.77787685394287
    },
    {
      "epoch": 18,
      "tr_loss": 0.5324587488174438,
      "tr_acc": 0.8163392857142857,
      "val_loss": 0.8406174373626709,
      "val_acc": 0.7226,
      "time": 19.035388708114624
    },
    {
      "epoch": 19,
      "tr_loss": 0.506465230669294,
      "tr_acc": 0.8266071428571429,
      "val_loss": 0.6528281073570251,
      "val_acc": 0.7688,
      "time": 19.005971670150757
    },
    {
      "epoch": 20,
      "tr_loss": 0.4932609006336757,
      "tr_acc": 0.8317857142857142,
      "val_loss": 1.0466916968345643,
      "val_acc": 0.6986,
      "time": 19.22269034385681
    },
    {
      "epoch": 21,
      "tr_loss": 0.4828163003921509,
      "tr_acc": 0.833125,
      "val_loss": 0.773635546875,
      "val_acc": 0.746,
      "time": 19.287344217300415
    },
    {
      "epoch": 22,
      "tr_loss": 0.4852078594480242,
      "tr_acc": 0.8330357142857143,
      "val_loss": 0.7372000687599182,
      "val_acc": 0.7504,
      "time": 19.71988034248352
    },
    {
      "epoch": 23,
      "tr_loss": 0.47654990485736304,
      "tr_acc": 0.8351339285714285,
      "val_loss": 0.7717583309173583,
      "val_acc": 0.7448,
      "time": 20.005586624145508
    },
    {
      "epoch": 24,
      "tr_loss": 0.47737092290605815,
      "tr_acc": 0.8370758928571429,
      "val_loss": 0.8762994291305543,
      "val_acc": 0.7212,
      "time": 19.199553966522217
    },
    {
      "epoch": 25,
      "tr_loss": 0.47762200679097855,
      "tr_acc": 0.8361160714285715,
      "val_loss": 0.8451186499595642,
      "val_acc": 0.717,
      "time": 19.09081506729126
    },
    {
      "epoch": 26,
      "tr_loss": 0.4878761374950409,
      "tr_acc": 0.8326339285714286,
      "val_loss": 0.8522501293182373,
      "val_acc": 0.705,
      "time": 19.492809057235718
    },
    {
      "epoch": 27,
      "tr_loss": 0.48770202721868244,
      "tr_acc": 0.8309598214285714,
      "val_loss": 0.7693247679710388,
      "val_acc": 0.7342,
      "time": 19.83601450920105
    },
    {
      "epoch": 28,
      "tr_loss": 0.48358982750347684,
      "tr_acc": 0.8325446428571428,
      "val_loss": 0.7476024457931518,
      "val_acc": 0.7402,
      "time": 19.37507128715515
    },
    {
      "epoch": 29,
      "tr_loss": 0.488519481420517,
      "tr_acc": 0.8325446428571428,
      "val_loss": 1.3496403135299682,
      "val_acc": 0.5884,
      "time": 18.93828773498535
    },
    {
      "epoch": 30,
      "tr_loss": 0.48389003021376475,
      "tr_acc": 0.8332142857142857,
      "val_loss": 0.8471674524307251,
      "val_acc": 0.7066,
      "time": 19.328372478485107
    },
    {
      "epoch": 31,
      "tr_loss": 0.49126653926713126,
      "tr_acc": 0.8316071428571429,
      "val_loss": 1.155250513267517,
      "val_acc": 0.685,
      "time": 19.42831778526306
    },
    {
      "epoch": 32,
      "tr_loss": 0.48123767801693507,
      "tr_acc": 0.8339285714285715,
      "val_loss": 1.2279073255538941,
      "val_acc": 0.6612,
      "time": 19.12275743484497
    },
    {
      "epoch": 33,
      "tr_loss": 0.47891680342810494,
      "tr_acc": 0.8358258928571428,
      "val_loss": 0.9737779482841492,
      "val_acc": 0.68,
      "time": 19.449142456054688
    },
    {
      "epoch": 34,
      "tr_loss": 0.48035011325563703,
      "tr_acc": 0.8355133928571429,
      "val_loss": 0.7054657072067261,
      "val_acc": 0.769,
      "time": 19.353335857391357
    },
    {
      "epoch": 35,
      "tr_loss": 0.46997513123920986,
      "tr_acc": 0.8383928571428572,
      "val_loss": 1.008313054561615,
      "val_acc": 0.6932,
      "time": 19.733131170272827
    },
    {
      "epoch": 36,
      "tr_loss": 0.47145342145647323,
      "tr_acc": 0.8379241071428571,
      "val_loss": 1.0797029043197632,
      "val_acc": 0.6574,
      "time": 19.42149519920349
    },
    {
      "epoch": 37,
      "tr_loss": 0.46343525188309803,
      "tr_acc": 0.8403794642857143,
      "val_loss": 0.9747082231521607,
      "val_acc": 0.6958,
      "time": 19.190855741500854
    },
    {
      "epoch": 38,
      "tr_loss": 0.4547022075312478,
      "tr_acc": 0.8449330357142857,
      "val_loss": 0.6803857480049134,
      "val_acc": 0.7752,
      "time": 19.325177907943726
    },
    {
      "epoch": 39,
      "tr_loss": 0.4536869638306754,
      "tr_acc": 0.8447098214285714,
      "val_loss": 0.8389005153656006,
      "val_acc": 0.7126,
      "time": 19.43012499809265
    },
    {
      "epoch": 40,
      "tr_loss": 0.44991553238459997,
      "tr_acc": 0.8449107142857143,
      "val_loss": 0.8901476422309875,
      "val_acc": 0.7072,
      "time": 19.402848720550537
    },
    {
      "epoch": 41,
      "tr_loss": 0.45034381696156095,
      "tr_acc": 0.8452008928571428,
      "val_loss": 0.758400100326538,
      "val_acc": 0.7458,
      "time": 19.054378986358643
    },
    {
      "epoch": 42,
      "tr_loss": 0.4382695894581931,
      "tr_acc": 0.8506473214285715,
      "val_loss": 0.5921908079624176,
      "val_acc": 0.8004,
      "time": 19.54884147644043
    },
    {
      "epoch": 43,
      "tr_loss": 0.44513172013419017,
      "tr_acc": 0.8470089285714286,
      "val_loss": 0.6598768781661988,
      "val_acc": 0.7812,
      "time": 19.78918147087097
    },
    {
      "epoch": 44,
      "tr_loss": 0.4339261129924229,
      "tr_acc": 0.8510714285714286,
      "val_loss": 0.9776663049697876,
      "val_acc": 0.694,
      "time": 19.390753984451294
    },
    {
      "epoch": 45,
      "tr_loss": 0.4455401195798601,
      "tr_acc": 0.8441964285714286,
      "val_loss": 1.4712955198287965,
      "val_acc": 0.5936,
      "time": 19.51113510131836
    },
    {
      "epoch": 46,
      "tr_loss": 0.4340937636579786,
      "tr_acc": 0.8496205357142858,
      "val_loss": 0.7376642724990845,
      "val_acc": 0.7574,
      "time": 19.122356176376343
    },
    {
      "epoch": 47,
      "tr_loss": 0.440736506325858,
      "tr_acc": 0.8487723214285714,
      "val_loss": 0.972326163482666,
      "val_acc": 0.6858,
      "time": 19.030628442764282
    },
    {
      "epoch": 48,
      "tr_loss": 0.433580117395946,
      "tr_acc": 0.8520982142857143,
      "val_loss": 0.8147967618942261,
      "val_acc": 0.7258,
      "time": 18.966347694396973
    },
    {
      "epoch": 49,
      "tr_loss": 0.4359496475969042,
      "tr_acc": 0.8515625,
      "val_loss": 1.027447548007965,
      "val_acc": 0.6754,
      "time": 19.860859155654907
    },
    {
      "epoch": 50,
      "tr_loss": 0.432040708065033,
      "tr_acc": 0.8523214285714286,
      "val_loss": 0.6752220101356506,
      "val_acc": 0.7804,
      "time": 19.674476146697998
    },
    {
      "epoch": 51,
      "tr_loss": 0.437411174263273,
      "tr_acc": 0.8506026785714286,
      "val_loss": 0.9076078269958496,
      "val_acc": 0.7078,
      "time": 18.954358100891113
    },
    {
      "epoch": 52,
      "tr_loss": 0.4292844799586705,
      "tr_acc": 0.8535714285714285,
      "val_loss": 0.6697386837959289,
      "val_acc": 0.7744,
      "time": 19.5818190574646
    },
    {
      "epoch": 53,
      "tr_loss": 0.4287569488797869,
      "tr_acc": 0.8529464285714285,
      "val_loss": 0.9188601334571839,
      "val_acc": 0.7132,
      "time": 19.77335262298584
    },
    {
      "epoch": 54,
      "tr_loss": 0.4238692569732666,
      "tr_acc": 0.8558705357142857,
      "val_loss": 0.7007367436408997,
      "val_acc": 0.7542,
      "time": 19.796791791915894
    },
    {
      "epoch": 55,
      "tr_loss": 0.4258213123253414,
      "tr_acc": 0.8547767857142857,
      "val_loss": 0.7668134190559387,
      "val_acc": 0.7478,
      "time": 19.40228796005249
    },
    {
      "epoch": 56,
      "tr_loss": 0.42183573825018744,
      "tr_acc": 0.8578571428571429,
      "val_loss": 0.7444033790588379,
      "val_acc": 0.744,
      "time": 19.298933506011963
    },
    {
      "epoch": 57,
      "tr_loss": 0.42911399296351843,
      "tr_acc": 0.8529017857142858,
      "val_loss": 0.6694805611610413,
      "val_acc": 0.7738,
      "time": 19.20785641670227
    },
    {
      "epoch": 58,
      "tr_loss": 0.4176573894705091,
      "tr_acc": 0.8579910714285715,
      "val_loss": 0.6371511302947998,
      "val_acc": 0.784,
      "time": 19.432776927947998
    },
    {
      "epoch": 59,
      "tr_loss": 0.416467011315482,
      "tr_acc": 0.8571205357142857,
      "val_loss": 0.6815613087654113,
      "val_acc": 0.7712,
      "time": 19.16212034225464
    },
    {
      "epoch": 60,
      "tr_loss": 0.4072764812197004,
      "tr_acc": 0.859375,
      "val_loss": 0.6507407782554626,
      "val_acc": 0.775,
      "time": 19.079591274261475
    },
    {
      "epoch": 61,
      "tr_loss": 0.4127131019319807,
      "tr_acc": 0.8560491071428571,
      "val_loss": 0.8206849603652954,
      "val_acc": 0.7424,
      "time": 19.25345778465271
    },
    {
      "epoch": 62,
      "tr_loss": 0.40447732874325343,
      "tr_acc": 0.8589955357142857,
      "val_loss": 1.6566690494537353,
      "val_acc": 0.5554,
      "time": 19.225349187850952
    },
    {
      "epoch": 63,
      "tr_loss": 0.40654283336230684,
      "tr_acc": 0.8624553571428571,
      "val_loss": 0.7159830076217651,
      "val_acc": 0.7586,
      "time": 19.46771764755249
    },
    {
      "epoch": 64,
      "tr_loss": 0.40747760721615384,
      "tr_acc": 0.860625,
      "val_loss": 0.9072174083709716,
      "val_acc": 0.6936,
      "time": 19.0752215385437
    },
    {
      "epoch": 65,
      "tr_loss": 0.4064377350466592,
      "tr_acc": 0.8615178571428571,
      "val_loss": 1.1012271944046021,
      "val_acc": 0.6712,
      "time": 18.93700361251831
    },
    {
      "epoch": 66,
      "tr_loss": 0.40590631314686365,
      "tr_acc": 0.8611607142857143,
      "val_loss": 0.5772922435760498,
      "val_acc": 0.8102,
      "time": 19.134233713150024
    },
    {
      "epoch": 67,
      "tr_loss": 0.40488229155540467,
      "tr_acc": 0.8623214285714286,
      "val_loss": 1.0238561225891114,
      "val_acc": 0.6662,
      "time": 19.206323623657227
    },
    {
      "epoch": 68,
      "tr_loss": 0.402479282617569,
      "tr_acc": 0.8647098214285714,
      "val_loss": 0.7542666316032409,
      "val_acc": 0.7556,
      "time": 19.562378883361816
    },
    {
      "epoch": 69,
      "tr_loss": 0.39143701195716857,
      "tr_acc": 0.8663169642857143,
      "val_loss": 0.6165632542610169,
      "val_acc": 0.7866,
      "time": 19.26551103591919
    },
    {
      "epoch": 70,
      "tr_loss": 0.3978028781924929,
      "tr_acc": 0.8629910714285715,
      "val_loss": 0.5824150057792663,
      "val_acc": 0.7976,
      "time": 19.412195682525635
    },
    {
      "epoch": 71,
      "tr_loss": 0.3885843655041286,
      "tr_acc": 0.8667857142857143,
      "val_loss": 0.7122285569190979,
      "val_acc": 0.7552,
      "time": 19.414392948150635
    },
    {
      "epoch": 72,
      "tr_loss": 0.3915173476082938,
      "tr_acc": 0.8671651785714286,
      "val_loss": 0.5444295117855072,
      "val_acc": 0.8138,
      "time": 19.262823581695557
    },
    {
      "epoch": 73,
      "tr_loss": 0.39221942033086504,
      "tr_acc": 0.8655803571428572,
      "val_loss": 0.5478007304191589,
      "val_acc": 0.8182,
      "time": 19.366654872894287
    },
    {
      "epoch": 74,
      "tr_loss": 0.38224542473043716,
      "tr_acc": 0.87125,
      "val_loss": 0.6646630891799927,
      "val_acc": 0.7738,
      "time": 19.872999906539917
    },
    {
      "epoch": 75,
      "tr_loss": 0.3769138252735138,
      "tr_acc": 0.8710491071428571,
      "val_loss": 0.8856813536643982,
      "val_acc": 0.719,
      "time": 19.06525158882141
    },
    {
      "epoch": 76,
      "tr_loss": 0.38442442791802545,
      "tr_acc": 0.8694419642857143,
      "val_loss": 0.6722953633308411,
      "val_acc": 0.7738,
      "time": 19.278493404388428
    },
    {
      "epoch": 77,
      "tr_loss": 0.3796495114053999,
      "tr_acc": 0.8708705357142857,
      "val_loss": 0.8237824115753174,
      "val_acc": 0.73,
      "time": 19.129340648651123
    },
    {
      "epoch": 78,
      "tr_loss": 0.3764947496141706,
      "tr_acc": 0.8708705357142857,
      "val_loss": 0.7085987557411194,
      "val_acc": 0.771,
      "time": 20.29740595817566
    },
    {
      "epoch": 79,
      "tr_loss": 0.37524865899767196,
      "tr_acc": 0.8714508928571428,
      "val_loss": 0.6750306960105896,
      "val_acc": 0.7842,
      "time": 19.0407977104187
    },
    {
      "epoch": 80,
      "tr_loss": 0.37560297574315754,
      "tr_acc": 0.8718080357142857,
      "val_loss": 0.6170874995231629,
      "val_acc": 0.791,
      "time": 19.05221128463745
    },
    {
      "epoch": 81,
      "tr_loss": 0.3677563712426594,
      "tr_acc": 0.87515625,
      "val_loss": 0.7031826506614685,
      "val_acc": 0.7554,
      "time": 19.254473209381104
    },
    {
      "epoch": 82,
      "tr_loss": 0.3598329219647816,
      "tr_acc": 0.8777455357142857,
      "val_loss": 0.6800933082580567,
      "val_acc": 0.7694,
      "time": 19.57872462272644
    },
    {
      "epoch": 83,
      "tr_loss": 0.3632925289017814,
      "tr_acc": 0.8774107142857143,
      "val_loss": 0.6844648552894592,
      "val_acc": 0.7694,
      "time": 19.206636428833008
    },
    {
      "epoch": 84,
      "tr_loss": 0.3631196212768555,
      "tr_acc": 0.8769196428571429,
      "val_loss": 0.6448943537712097,
      "val_acc": 0.7936,
      "time": 19.563546895980835
    },
    {
      "epoch": 85,
      "tr_loss": 0.3612686554023198,
      "tr_acc": 0.8764508928571428,
      "val_loss": 0.7737819094657898,
      "val_acc": 0.752,
      "time": 20.222745180130005
    },
    {
      "epoch": 86,
      "tr_loss": 0.3558495931114469,
      "tr_acc": 0.8777232142857143,
      "val_loss": 0.6696186063766479,
      "val_acc": 0.7828,
      "time": 19.42005729675293
    },
    {
      "epoch": 87,
      "tr_loss": 0.3556092096226556,
      "tr_acc": 0.8777678571428571,
      "val_loss": 0.6506076174736023,
      "val_acc": 0.7802,
      "time": 19.18477749824524
    },
    {
      "epoch": 88,
      "tr_loss": 0.34960222959518433,
      "tr_acc": 0.8797767857142857,
      "val_loss": 0.6119043899536133,
      "val_acc": 0.7988,
      "time": 19.394855976104736
    },
    {
      "epoch": 89,
      "tr_loss": 0.3501691732236317,
      "tr_acc": 0.879375,
      "val_loss": 0.5193186385154724,
      "val_acc": 0.8218,
      "time": 19.486392498016357
    },
    {
      "epoch": 90,
      "tr_loss": 0.34790767541953493,
      "tr_acc": 0.88078125,
      "val_loss": 0.7478139218330383,
      "val_acc": 0.7584,
      "time": 19.050761699676514
    },
    {
      "epoch": 91,
      "tr_loss": 0.3442088024956839,
      "tr_acc": 0.8827901785714286,
      "val_loss": 0.7096650656700134,
      "val_acc": 0.7588,
      "time": 19.22493863105774
    },
    {
      "epoch": 92,
      "tr_loss": 0.34525233839239394,
      "tr_acc": 0.8816964285714286,
      "val_loss": 0.6431186641693115,
      "val_acc": 0.7884,
      "time": 19.213711977005005
    },
    {
      "epoch": 93,
      "tr_loss": 0.3440259827034814,
      "tr_acc": 0.8825892857142857,
      "val_loss": 0.6015724174499512,
      "val_acc": 0.8008,
      "time": 19.78122878074646
    },
    {
      "epoch": 94,
      "tr_loss": 0.3440508527415139,
      "tr_acc": 0.8833705357142857,
      "val_loss": 0.6195181663513184,
      "val_acc": 0.7864,
      "time": 19.246012687683105
    },
    {
      "epoch": 95,
      "tr_loss": 0.33834375960486274,
      "tr_acc": 0.8852678571428572,
      "val_loss": 0.5905153721809387,
      "val_acc": 0.8012,
      "time": 19.198920011520386
    },
    {
      "epoch": 96,
      "tr_loss": 0.3418666239295687,
      "tr_acc": 0.8829910714285715,
      "val_loss": 0.651559823513031,
      "val_acc": 0.7892,
      "time": 19.14415693283081
    },
    {
      "epoch": 97,
      "tr_loss": 0.3372415247985295,
      "tr_acc": 0.88515625,
      "val_loss": 0.6917884008407593,
      "val_acc": 0.771,
      "time": 19.768313884735107
    },
    {
      "epoch": 98,
      "tr_loss": 0.33629433521202634,
      "tr_acc": 0.88578125,
      "val_loss": 0.7516814296722412,
      "val_acc": 0.7578,
      "time": 19.14032006263733
    },
    {
      "epoch": 99,
      "tr_loss": 0.32929711273738316,
      "tr_acc": 0.88515625,
      "val_loss": 0.5870041439056396,
      "val_acc": 0.8054,
      "time": 19.403713941574097
    },
    {
      "epoch": 100,
      "tr_loss": 0.32771454700401853,
      "tr_acc": 0.8877901785714286,
      "val_loss": 0.5388271114826202,
      "val_acc": 0.8178,
      "time": 19.577033519744873
    },
    {
      "epoch": 101,
      "tr_loss": 0.32290208978312357,
      "tr_acc": 0.889375,
      "val_loss": 0.5828034376621246,
      "val_acc": 0.7956,
      "time": 19.471086502075195
    },
    {
      "epoch": 102,
      "tr_loss": 0.3198263257741928,
      "tr_acc": 0.89109375,
      "val_loss": 0.8872185960769653,
      "val_acc": 0.7414,
      "time": 19.388740301132202
    },
    {
      "epoch": 103,
      "tr_loss": 0.32449490317276547,
      "tr_acc": 0.89015625,
      "val_loss": 0.6832921902656555,
      "val_acc": 0.7784,
      "time": 19.31095314025879
    },
    {
      "epoch": 104,
      "tr_loss": 0.31697676343577247,
      "tr_acc": 0.8916294642857143,
      "val_loss": 0.6485164765357971,
      "val_acc": 0.7862,
      "time": 20.05691385269165
    },
    {
      "epoch": 105,
      "tr_loss": 0.31677083679607937,
      "tr_acc": 0.8933482142857143,
      "val_loss": 0.5171618501663208,
      "val_acc": 0.82,
      "time": 19.057153940200806
    },
    {
      "epoch": 106,
      "tr_loss": 0.3138999666486468,
      "tr_acc": 0.8919642857142858,
      "val_loss": 0.5122671947479248,
      "val_acc": 0.8256,
      "time": 19.28652286529541
    },
    {
      "epoch": 107,
      "tr_loss": 0.316217982513564,
      "tr_acc": 0.8906696428571429,
      "val_loss": 0.6971290647506714,
      "val_acc": 0.7666,
      "time": 19.360864639282227
    },
    {
      "epoch": 108,
      "tr_loss": 0.3154340880257743,
      "tr_acc": 0.8922098214285714,
      "val_loss": 0.6415714905738831,
      "val_acc": 0.7848,
      "time": 19.174970149993896
    },
    {
      "epoch": 109,
      "tr_loss": 0.30819296777248384,
      "tr_acc": 0.8953571428571429,
      "val_loss": 0.44640857949256896,
      "val_acc": 0.842,
      "time": 19.46633768081665
    },
    {
      "epoch": 110,
      "tr_loss": 0.3043320918083191,
      "tr_acc": 0.8951116071428571,
      "val_loss": 0.753755357837677,
      "val_acc": 0.755,
      "time": 19.137589693069458
    },
    {
      "epoch": 111,
      "tr_loss": 0.3084465545415878,
      "tr_acc": 0.8950223214285714,
      "val_loss": 0.5354485016822815,
      "val_acc": 0.8272,
      "time": 19.41006350517273
    },
    {
      "epoch": 112,
      "tr_loss": 0.3029248125212533,
      "tr_acc": 0.8959151785714285,
      "val_loss": 0.9392397218704224,
      "val_acc": 0.7274,
      "time": 19.34323811531067
    },
    {
      "epoch": 113,
      "tr_loss": 0.30142085066863467,
      "tr_acc": 0.898125,
      "val_loss": 0.46456291790008547,
      "val_acc": 0.84,
      "time": 19.333667993545532
    },
    {
      "epoch": 114,
      "tr_loss": 0.3012930500507355,
      "tr_acc": 0.8987723214285714,
      "val_loss": 0.5413933923721314,
      "val_acc": 0.8184,
      "time": 19.011290788650513
    },
    {
      "epoch": 115,
      "tr_loss": 0.29601513615676334,
      "tr_acc": 0.9002008928571429,
      "val_loss": 0.6870137090682984,
      "val_acc": 0.7794,
      "time": 19.114603757858276
    },
    {
      "epoch": 116,
      "tr_loss": 0.295756699528013,
      "tr_acc": 0.8984375,
      "val_loss": 0.6493212093353271,
      "val_acc": 0.7828,
      "time": 19.011475086212158
    },
    {
      "epoch": 117,
      "tr_loss": 0.2916837695666722,
      "tr_acc": 0.9003348214285715,
      "val_loss": 0.5017394726276397,
      "val_acc": 0.8334,
      "time": 19.66882085800171
    },
    {
      "epoch": 118,
      "tr_loss": 0.28661673060485293,
      "tr_acc": 0.9024776785714286,
      "val_loss": 0.6821530920028687,
      "val_acc": 0.776,
      "time": 20.283828735351562
    },
    {
      "epoch": 119,
      "tr_loss": 0.28586190496172226,
      "tr_acc": 0.9031473214285715,
      "val_loss": 0.7040130753517151,
      "val_acc": 0.7686,
      "time": 19.193268060684204
    },
    {
      "epoch": 120,
      "tr_loss": 0.2844016738448824,
      "tr_acc": 0.9018973214285714,
      "val_loss": 1.0059854557037353,
      "val_acc": 0.7054,
      "time": 19.08165192604065
    },
    {
      "epoch": 121,
      "tr_loss": 0.2832309175389154,
      "tr_acc": 0.90328125,
      "val_loss": 0.48567182664871217,
      "val_acc": 0.8332,
      "time": 19.405644416809082
    },
    {
      "epoch": 122,
      "tr_loss": 0.2804572181190763,
      "tr_acc": 0.9028571428571428,
      "val_loss": 0.5183651760101319,
      "val_acc": 0.827,
      "time": 18.927934885025024
    },
    {
      "epoch": 123,
      "tr_loss": 0.2807956392424447,
      "tr_acc": 0.9034375,
      "val_loss": 0.4472147838115692,
      "val_acc": 0.8414,
      "time": 19.31222677230835
    },
    {
      "epoch": 124,
      "tr_loss": 0.2790163247925895,
      "tr_acc": 0.9064285714285715,
      "val_loss": 0.5630181254863739,
      "val_acc": 0.8124,
      "time": 19.829204082489014
    },
    {
      "epoch": 125,
      "tr_loss": 0.2803773332493646,
      "tr_acc": 0.9051785714285714,
      "val_loss": 0.5249586275100708,
      "val_acc": 0.821,
      "time": 19.04319977760315
    },
    {
      "epoch": 126,
      "tr_loss": 0.27614813770566665,
      "tr_acc": 0.9055803571428571,
      "val_loss": 0.5055230105400086,
      "val_acc": 0.8204,
      "time": 19.495835781097412
    },
    {
      "epoch": 127,
      "tr_loss": 0.27426296600273675,
      "tr_acc": 0.9064732142857143,
      "val_loss": 0.4639365875244141,
      "val_acc": 0.8448,
      "time": 19.311245441436768
    },
    {
      "epoch": 128,
      "tr_loss": 0.2740064965827124,
      "tr_acc": 0.9063169642857143,
      "val_loss": 0.6148939388275146,
      "val_acc": 0.7992,
      "time": 19.056129217147827
    },
    {
      "epoch": 129,
      "tr_loss": 0.27198966298784527,
      "tr_acc": 0.9067410714285714,
      "val_loss": 0.44496811027526856,
      "val_acc": 0.8498,
      "time": 19.17049288749695
    },
    {
      "epoch": 130,
      "tr_loss": 0.26769786059856415,
      "tr_acc": 0.9090848214285714,
      "val_loss": 0.5044639718055726,
      "val_acc": 0.8304,
      "time": 19.20814871788025
    },
    {
      "epoch": 131,
      "tr_loss": 0.2711403864622116,
      "tr_acc": 0.9075892857142858,
      "val_loss": 0.40387672843933103,
      "val_acc": 0.8626,
      "time": 19.119674921035767
    },
    {
      "epoch": 132,
      "tr_loss": 0.26509698382445746,
      "tr_acc": 0.9086830357142858,
      "val_loss": 0.4135971993923187,
      "val_acc": 0.8588,
      "time": 19.623637676239014
    },
    {
      "epoch": 133,
      "tr_loss": 0.2645859371764319,
      "tr_acc": 0.9101116071428571,
      "val_loss": 0.48286151432991026,
      "val_acc": 0.8396,
      "time": 19.241002321243286
    },
    {
      "epoch": 134,
      "tr_loss": 0.256721990278789,
      "tr_acc": 0.9116071428571428,
      "val_loss": 0.44337586340904234,
      "val_acc": 0.8456,
      "time": 19.31498694419861
    },
    {
      "epoch": 135,
      "tr_loss": 0.25943325570651465,
      "tr_acc": 0.9121875,
      "val_loss": 0.44073460936546327,
      "val_acc": 0.8454,
      "time": 19.593326807022095
    },
    {
      "epoch": 136,
      "tr_loss": 0.2602159613370895,
      "tr_acc": 0.9108705357142857,
      "val_loss": 0.7625508421897889,
      "val_acc": 0.76,
      "time": 18.978227138519287
    },
    {
      "epoch": 137,
      "tr_loss": 0.25510910059724534,
      "tr_acc": 0.9131696428571429,
      "val_loss": 0.5787304307937622,
      "val_acc": 0.8064,
      "time": 19.034768104553223
    },
    {
      "epoch": 138,
      "tr_loss": 0.2547712102958134,
      "tr_acc": 0.9142633928571429,
      "val_loss": 0.44730004415512087,
      "val_acc": 0.849,
      "time": 19.46475887298584
    },
    {
      "epoch": 139,
      "tr_loss": 0.25262322042669566,
      "tr_acc": 0.9146875,
      "val_loss": 0.5592072568893433,
      "val_acc": 0.8132,
      "time": 19.13030195236206
    },
    {
      "epoch": 140,
      "tr_loss": 0.2494435876607895,
      "tr_acc": 0.9163392857142857,
      "val_loss": 0.4469952035903931,
      "val_acc": 0.8466,
      "time": 18.931657075881958
    },
    {
      "epoch": 141,
      "tr_loss": 0.24458365406308855,
      "tr_acc": 0.91609375,
      "val_loss": 0.391170783996582,
      "val_acc": 0.8672,
      "time": 19.117486476898193
    },
    {
      "epoch": 142,
      "tr_loss": 0.24765665471553802,
      "tr_acc": 0.9159375,
      "val_loss": 0.4603018238067627,
      "val_acc": 0.8392,
      "time": 20.096874475479126
    },
    {
      "epoch": 143,
      "tr_loss": 0.24293018324034554,
      "tr_acc": 0.9175,
      "val_loss": 0.4858679950237274,
      "val_acc": 0.8358,
      "time": 19.38238000869751
    },
    {
      "epoch": 144,
      "tr_loss": 0.24305624978882925,
      "tr_acc": 0.9179241071428571,
      "val_loss": 0.5302238634586334,
      "val_acc": 0.8212,
      "time": 19.381741523742676
    },
    {
      "epoch": 145,
      "tr_loss": 0.23941376217773983,
      "tr_acc": 0.9185044642857143,
      "val_loss": 0.4734880401134491,
      "val_acc": 0.8476,
      "time": 19.359074592590332
    },
    {
      "epoch": 146,
      "tr_loss": 0.2403414591721126,
      "tr_acc": 0.9191294642857143,
      "val_loss": 0.552069494342804,
      "val_acc": 0.8238,
      "time": 19.062520742416382
    },
    {
      "epoch": 147,
      "tr_loss": 0.23624075583049228,
      "tr_acc": 0.9203348214285715,
      "val_loss": 0.45280786905288695,
      "val_acc": 0.8444,
      "time": 19.389594793319702
    },
    {
      "epoch": 148,
      "tr_loss": 0.23729131885937282,
      "tr_acc": 0.9211383928571428,
      "val_loss": 0.46839005188941957,
      "val_acc": 0.8492,
      "time": 19.066700220108032
    },
    {
      "epoch": 149,
      "tr_loss": 0.2356513546194349,
      "tr_acc": 0.9198214285714286,
      "val_loss": 0.3504387791156769,
      "val_acc": 0.8814,
      "time": 19.256372690200806
    },
    {
      "epoch": 150,
      "tr_loss": 0.2278195207459586,
      "tr_acc": 0.9228348214285714,
      "val_loss": 0.45097306230068207,
      "val_acc": 0.8478,
      "time": 19.468900680541992
    },
    {
      "epoch": 151,
      "tr_loss": 0.23258100288254874,
      "tr_acc": 0.9199330357142858,
      "val_loss": 0.44578650426864624,
      "val_acc": 0.8546,
      "time": 19.14445400238037
    },
    {
      "epoch": 152,
      "tr_loss": 0.23007381515843528,
      "tr_acc": 0.9234151785714285,
      "val_loss": 0.3718927092552185,
      "val_acc": 0.8796,
      "time": 19.149402618408203
    },
    {
      "epoch": 153,
      "tr_loss": 0.2283155830843108,
      "tr_acc": 0.9242410714285715,
      "val_loss": 0.4021569781780243,
      "val_acc": 0.8658,
      "time": 19.27197766304016
    },
    {
      "epoch": 154,
      "tr_loss": 0.23138849445751736,
      "tr_acc": 0.9207366071428571,
      "val_loss": 0.3955093773365021,
      "val_acc": 0.8618,
      "time": 19.134209871292114
    },
    {
      "epoch": 155,
      "tr_loss": 0.2270921014036451,
      "tr_acc": 0.92375,
      "val_loss": 0.38379128522872924,
      "val_acc": 0.8724,
      "time": 19.09255814552307
    },
    {
      "epoch": 156,
      "tr_loss": 0.2237786716222763,
      "tr_acc": 0.9244196428571428,
      "val_loss": 0.38716274976730347,
      "val_acc": 0.871,
      "time": 19.215270519256592
    },
    {
      "epoch": 157,
      "tr_loss": 0.21886006687368664,
      "tr_acc": 0.9246875,
      "val_loss": 0.5048689338684083,
      "val_acc": 0.8456,
      "time": 19.32940173149109
    },
    {
      "epoch": 158,
      "tr_loss": 0.21582586084093366,
      "tr_acc": 0.9277901785714285,
      "val_loss": 0.4402419095993042,
      "val_acc": 0.8562,
      "time": 19.14400625228882
    },
    {
      "epoch": 159,
      "tr_loss": 0.2158704343863896,
      "tr_acc": 0.9272767857142857,
      "val_loss": 0.3923405135154724,
      "val_acc": 0.869,
      "time": 19.162349700927734
    },
    {
      "epoch": 160,
      "tr_loss": 0.21479679116180964,
      "tr_acc": 0.92875,
      "val_loss": 0.4130950336456299,
      "val_acc": 0.865,
      "time": 19.297662496566772
    },
    {
      "epoch": 161,
      "tr_loss": 0.21372037649154663,
      "tr_acc": 0.9265178571428572,
      "val_loss": 0.4369184310436249,
      "val_acc": 0.8592,
      "time": 19.20601463317871
    },
    {
      "epoch": 162,
      "tr_loss": 0.20814263314008713,
      "tr_acc": 0.9304017857142857,
      "val_loss": 0.5289402344226837,
      "val_acc": 0.8292,
      "time": 19.304822206497192
    },
    {
      "epoch": 163,
      "tr_loss": 0.20682915125574383,
      "tr_acc": 0.9292633928571429,
      "val_loss": 0.4708651760578155,
      "val_acc": 0.8472,
      "time": 19.11202096939087
    },
    {
      "epoch": 164,
      "tr_loss": 0.20669229383979526,
      "tr_acc": 0.9295535714285714,
      "val_loss": 0.3623667623519897,
      "val_acc": 0.8778,
      "time": 19.505078554153442
    },
    {
      "epoch": 165,
      "tr_loss": 0.2044301483460835,
      "tr_acc": 0.9306473214285714,
      "val_loss": 0.45455886921882627,
      "val_acc": 0.8484,
      "time": 19.648106575012207
    },
    {
      "epoch": 166,
      "tr_loss": 0.20663209417036602,
      "tr_acc": 0.9299107142857143,
      "val_loss": 0.40900910234451293,
      "val_acc": 0.8652,
      "time": 19.39695167541504
    },
    {
      "epoch": 167,
      "tr_loss": 0.20200665635722023,
      "tr_acc": 0.9333482142857142,
      "val_loss": 0.4273872022151947,
      "val_acc": 0.861,
      "time": 18.95317792892456
    },
    {
      "epoch": 168,
      "tr_loss": 0.19844300499984197,
      "tr_acc": 0.9327678571428571,
      "val_loss": 0.44790783700942993,
      "val_acc": 0.8588,
      "time": 19.045854091644287
    },
    {
      "epoch": 169,
      "tr_loss": 0.19936028114386967,
      "tr_acc": 0.9314732142857143,
      "val_loss": 0.40326863412857056,
      "val_acc": 0.8624,
      "time": 19.114298582077026
    },
    {
      "epoch": 170,
      "tr_loss": 0.19829142093658447,
      "tr_acc": 0.9327678571428571,
      "val_loss": 0.343082581949234,
      "val_acc": 0.8922,
      "time": 19.56578230857849
    },
    {
      "epoch": 171,
      "tr_loss": 0.19249800418104443,
      "tr_acc": 0.9348660714285715,
      "val_loss": 0.41798660984039304,
      "val_acc": 0.8586,
      "time": 18.996403455734253
    },
    {
      "epoch": 172,
      "tr_loss": 0.19026430317333767,
      "tr_acc": 0.9362946428571428,
      "val_loss": 0.42612703790664674,
      "val_acc": 0.8554,
      "time": 19.540918111801147
    },
    {
      "epoch": 173,
      "tr_loss": 0.1890579166156905,
      "tr_acc": 0.9378794642857143,
      "val_loss": 0.35136341152191164,
      "val_acc": 0.8814,
      "time": 19.640647888183594
    },
    {
      "epoch": 174,
      "tr_loss": 0.18473003945180347,
      "tr_acc": 0.9374776785714286,
      "val_loss": 0.3828438047885895,
      "val_acc": 0.877,
      "time": 19.108846187591553
    },
    {
      "epoch": 175,
      "tr_loss": 0.1834007216351373,
      "tr_acc": 0.9384151785714285,
      "val_loss": 0.3897699263572693,
      "val_acc": 0.8728,
      "time": 19.527475118637085
    },
    {
      "epoch": 176,
      "tr_loss": 0.18231190941163472,
      "tr_acc": 0.9384598214285714,
      "val_loss": 0.3627476529598236,
      "val_acc": 0.8806,
      "time": 19.212952613830566
    },
    {
      "epoch": 177,
      "tr_loss": 0.17891916947705405,
      "tr_acc": 0.9399776785714286,
      "val_loss": 0.39479382438659666,
      "val_acc": 0.87,
      "time": 20.13129687309265
    },
    {
      "epoch": 178,
      "tr_loss": 0.18033733802182333,
      "tr_acc": 0.9395982142857143,
      "val_loss": 0.3918858453273773,
      "val_acc": 0.871,
      "time": 19.151132106781006
    },
    {
      "epoch": 179,
      "tr_loss": 0.17248215419905527,
      "tr_acc": 0.9423214285714285,
      "val_loss": 0.3489290946006775,
      "val_acc": 0.8808,
      "time": 18.925564289093018
    },
    {
      "epoch": 180,
      "tr_loss": 0.17136939282928193,
      "tr_acc": 0.9427455357142858,
      "val_loss": 0.42584962944984434,
      "val_acc": 0.8612,
      "time": 19.401734590530396
    },
    {
      "epoch": 181,
      "tr_loss": 0.17081522805350166,
      "tr_acc": 0.9419196428571428,
      "val_loss": 0.32501912937164307,
      "val_acc": 0.8908,
      "time": 19.21200704574585
    },
    {
      "epoch": 182,
      "tr_loss": 0.16853676859821592,
      "tr_acc": 0.9430803571428571,
      "val_loss": 0.345531405878067,
      "val_acc": 0.8848,
      "time": 19.259117364883423
    },
    {
      "epoch": 183,
      "tr_loss": 0.16192837604454585,
      "tr_acc": 0.9456473214285714,
      "val_loss": 0.3700636705875397,
      "val_acc": 0.8776,
      "time": 19.19237780570984
    },
    {
      "epoch": 184,
      "tr_loss": 0.1593466437288693,
      "tr_acc": 0.9471205357142857,
      "val_loss": 0.37808375191688537,
      "val_acc": 0.8808,
      "time": 19.572198152542114
    },
    {
      "epoch": 185,
      "tr_loss": 0.15813713520765305,
      "tr_acc": 0.9473214285714285,
      "val_loss": 0.37597975492477415,
      "val_acc": 0.8762,
      "time": 18.922295331954956
    },
    {
      "epoch": 186,
      "tr_loss": 0.15825772336551122,
      "tr_acc": 0.9471205357142857,
      "val_loss": 0.3303771203994751,
      "val_acc": 0.886,
      "time": 19.619306087493896
    },
    {
      "epoch": 187,
      "tr_loss": 0.1526108440756798,
      "tr_acc": 0.9493080357142857,
      "val_loss": 0.3167913964748383,
      "val_acc": 0.8922,
      "time": 19.41528058052063
    },
    {
      "epoch": 188,
      "tr_loss": 0.15067722925118038,
      "tr_acc": 0.9504464285714286,
      "val_loss": 0.306528884267807,
      "val_acc": 0.8958,
      "time": 18.94408917427063
    },
    {
      "epoch": 189,
      "tr_loss": 0.1450096247451646,
      "tr_acc": 0.9516294642857143,
      "val_loss": 0.2994710219144821,
      "val_acc": 0.9016,
      "time": 19.201160192489624
    },
    {
      "epoch": 190,
      "tr_loss": 0.14433044650724955,
      "tr_acc": 0.9534375,
      "val_loss": 0.3123198432445526,
      "val_acc": 0.8998,
      "time": 19.055422067642212
    },
    {
      "epoch": 191,
      "tr_loss": 0.1379568347334862,
      "tr_acc": 0.9543080357142857,
      "val_loss": 0.31091751856803895,
      "val_acc": 0.8974,
      "time": 19.180556058883667
    },
    {
      "epoch": 192,
      "tr_loss": 0.1345674841105938,
      "tr_acc": 0.95640625,
      "val_loss": 0.29532148952484133,
      "val_acc": 0.9028,
      "time": 19.134177446365356
    },
    {
      "epoch": 193,
      "tr_loss": 0.1325540320788111,
      "tr_acc": 0.9568973214285714,
      "val_loss": 0.28668386716842653,
      "val_acc": 0.9078,
      "time": 19.29587697982788
    },
    {
      "epoch": 194,
      "tr_loss": 0.12965770993913922,
      "tr_acc": 0.9574776785714286,
      "val_loss": 0.3018924300670624,
      "val_acc": 0.9032,
      "time": 18.845690727233887
    },
    {
      "epoch": 195,
      "tr_loss": 0.12498827184949603,
      "tr_acc": 0.9589285714285715,
      "val_loss": 0.28493853492736815,
      "val_acc": 0.9066,
      "time": 19.052922248840332
    },
    {
      "epoch": 196,
      "tr_loss": 0.119646372624806,
      "tr_acc": 0.9624107142857142,
      "val_loss": 0.2738759416103363,
      "val_acc": 0.9104,
      "time": 19.75482749938965
    },
    {
      "epoch": 197,
      "tr_loss": 0.1183401124392237,
      "tr_acc": 0.9619419642857143,
      "val_loss": 0.2651756881475449,
      "val_acc": 0.915,
      "time": 18.878201484680176
    },
    {
      "epoch": 198,
      "tr_loss": 0.11356861450842448,
      "tr_acc": 0.9650669642857143,
      "val_loss": 0.25276293110847475,
      "val_acc": 0.9124,
      "time": 19.52704358100891
    },
    {
      "epoch": 199,
      "tr_loss": 0.10636764098490988,
      "tr_acc": 0.96609375,
      "val_loss": 0.2631210480690002,
      "val_acc": 0.9134,
      "time": 18.98369073867798
    }
  ]
}